snkit/__init__.py
snkit/network.py
snkit/utils.py
snkit-1.9.0.dist-info/LICENSE
snkit-1.9.0.dist-info/METADATA
snkit-1.9.0.dist-info/WHEEL
snkit-1.9.0.dist-info/top_level.txt
snkit-1.9.0.dist-info/RECORD
