Metadata-Version: 2.1
Name: snkit
Version: 1.9.0
Summary: a spatial networks toolkit
Home-page: https://github.com/tomalrussell/snkit
Author: Tom Russell
Author-email: tomalrussell@gmail.com
License: MIT License
Classifier: Development Status :: 4 - Beta
Classifier: Intended Audience :: Developers
Classifier: License :: OSI Approved :: MIT License
Classifier: Programming Language :: Python
Classifier: Programming Language :: Python :: 3
Classifier: Topic :: Scientific/Engineering :: GIS
Classifier: Topic :: Utilities
License-File: LICENSE
Requires-Dist: geopandas >=0.13
Requires-Dist: shapely >=2.0
Provides-Extra: dev
Requires-Dist: black ; extra == 'dev'
Requires-Dist: mypy ; extra == 'dev'
Requires-Dist: nbstripout ; extra == 'dev'
Requires-Dist: pre-commit ; extra == 'dev'
Requires-Dist: pytest ; extra == 'dev'
Requires-Dist: pytest-cov ; extra == 'dev'
Requires-Dist: ruff ; extra == 'dev'
Provides-Extra: docs
Requires-Dist: sphinx ; extra == 'docs'
Requires-Dist: m2r2 ; extra == 'docs'
Provides-Extra: networkx
Requires-Dist: networkx >=3.0 ; extra == 'networkx'
